cromshell/__init__.py
cromshell/__main__.py
cromshell/log.py
cromshell/abort/__init__.py
cromshell/abort/command.py
cromshell/alias/__init__.py
cromshell/alias/command.py
cromshell/cost/__init__.py
cromshell/cost/command.py
cromshell/counts/__init__.py
cromshell/counts/command.py
cromshell/list/__init__.py
cromshell/list/command.py
cromshell/list_outputs/__init__.py
cromshell/list_outputs/command.py
cromshell/logs/__init__.py
cromshell/logs/command.py
cromshell/metadata/__init__.py
cromshell/metadata/command.py
cromshell/slim_metadata/__init__.py
cromshell/slim_metadata/command.py
cromshell/status/__init__.py
cromshell/status/command.py
cromshell/submit/__init__.py
cromshell/submit/command.py
cromshell/timing/__init__.py
cromshell/timing/command.py
cromshell/update_server/__init__.py
cromshell/update_server/command.py
cromshell/utilities/__init__.py
cromshell/utilities/command_setup_utils.py
cromshell/utilities/config_options_file_utils.py
cromshell/utilities/cromshellconfig.py
cromshell/utilities/http_utils.py
cromshell/utilities/io_utils.py
cromshell/utilities/miniwdl_utils.py
cromshell/utilities/submissions_file_utils.py
cromshell/utilities/womtool_utils.py
cromshell/utilities/workflow_id_utils.py
cromshell/utilities/workflow_status_utils.py
cromshell/validate/__init__.py
cromshell/validate/command.py
cromshell-2.1.1.dist-info/LICENSE
cromshell-2.1.1.dist-info/METADATA
cromshell-2.1.1.dist-info/WHEEL
cromshell-2.1.1.dist-info/entry_points.txt
cromshell-2.1.1.dist-info/top_level.txt
cromshell-2.1.1.dist-info/RECORD
