Metadata-Version: 2.1
Name: cromshell
Version: 2.1.1
Summary: Command Line Interface (CLI) for Cromwell servers
Home-page: https://github.com/broadinstitute/cromshell
Author: Jonn Smith, Louis Bergelson, Beri Shifaw
Author-email: jonn@broadinstitute.org, louisb@broadinstitute.org, bshifaw@broadinstitute.org
License: BSD 3-Clause
Project-URL: Homepage, https://github.com/broadinstitute/cromshell
Project-URL: Bug Tracker, https://github.com/broadinstitute/cromshell/issues
Classifier: Development Status :: 5 - Production/Stable
Classifier: Intended Audience :: Science/Research
Classifier: License :: OSI Approved :: BSD License
Classifier: Natural Language :: English
Classifier: Operating System :: OS Independent
Classifier: Programming Language :: Python :: 3.7
Classifier: Programming Language :: Python :: 3.8
Classifier: Programming Language :: Python :: 3.9
Classifier: Programming Language :: Python :: 3.10
Classifier: Programming Language :: Python :: Implementation :: CPython
Requires-Python: >=3.7
License-File: LICENSE
Requires-Dist: gcsfs >=2022.3.0
Requires-Dist: google-cloud-bigquery >=3.5.0
Requires-Dist: termcolor >=1.1.0
Requires-Dist: click >=8.0.0
Requires-Dist: requests >=2.27.1
Requires-Dist: pygments >=2.12.0
Requires-Dist: tabulate >=0.8.9
Requires-Dist: miniwdl >=1.10.0
